{
  "meta": {
    "format": "httpie",
    "version": "1.0.0",
    "contentType": "collection",
    "schema": "https://schema.httpie.io/1.0.0.json",
    "docs": "https://httpie.io/r/help/export-from-httpie",
    "source": "HTTPie Desktop 2025.2.0"
  },
  "entry": {
    "name": "realtime order monitor",
    "icon": {
      "name": "default",
      "color": "gray"
    },
    "auth": {
      "type": "none"
    },
    "requests": [
      {
        "name": "RECEIVED order",
        "url": "http://localhost:8080/orders/c3fe75bf-a5ff-4026-a261-097112fead43",
        "method": "GET",
        "headers": [],
        "queryParams": [],
        "pathParams": [],
        "auth": {
          "type": "inherited"
        },
        "body": {
          "type": "none",
          "file": {
            "name": ""
          },
          "text": {
            "value": "",
            "format": "application/json"
          },
          "form": {
            "isMultipart": false,
            "fields": []
          },
          "graphql": {
            "query": "",
            "variables": ""
          }
        }
      },
      {
        "name": "RECEIVED => BEING_PREPARED order",
        "url": "http://localhost:8080/orders/c3fe75bf-a5ff-4026-a261-097112fead43",
        "method": "PATCH",
        "headers": [],
        "queryParams": [],
        "pathParams": [],
        "auth": {
          "type": "inherited"
        },
        "body": {
          "type": "text",
          "file": {
            "name": ""
          },
          "text": {
            "value": "{\n  \"status\": \"BEING_PREPARED\"\n}",
            "format": "application/json"
          },
          "form": {
            "isMultipart": false,
            "fields": []
          },
          "graphql": {
            "query": "",
            "variables": ""
          }
        }
      },
      {
        "name": "READY order",
        "url": "http://localhost:8080/orders/d397135e-70ff-4d17-a003-8e8aa17ef12b",
        "method": "GET",
        "headers": [],
        "queryParams": [],
        "pathParams": [],
        "auth": {
          "type": "inherited"
        },
        "body": {
          "type": "none",
          "file": {
            "name": ""
          },
          "text": {
            "value": "",
            "format": "application/json"
          },
          "form": {
            "isMultipart": false,
            "fields": []
          },
          "graphql": {
            "query": "",
            "variables": ""
          }
        }
      },
      {
        "name": "READY => IN_TRANSIT order",
        "url": "http://localhost:8080/orders/d397135e-70ff-4d17-a003-8e8aa17ef12b",
        "method": "PATCH",
        "headers": [],
        "queryParams": [],
        "pathParams": [],
        "auth": {
          "type": "inherited"
        },
        "body": {
          "type": "text",
          "file": {
            "name": ""
          },
          "text": {
            "value": "{\n  \"status\": \"IN_TRANSIT\"\n}",
            "format": "application/json"
          },
          "form": {
            "isMultipart": false,
            "fields": []
          },
          "graphql": {
            "query": "",
            "variables": ""
          }
        }
      },
      {
        "name": "IN_TRANSIT order",
        "url": "http://localhost:8080/orders/f8afdb91-7496-457a-95b6-a5a07d4976a3",
        "method": "GET",
        "headers": [],
        "queryParams": [],
        "pathParams": [],
        "auth": {
          "type": "inherited"
        },
        "body": {
          "type": "none",
          "file": {
            "name": ""
          },
          "text": {
            "value": "",
            "format": "application/json"
          },
          "form": {
            "isMultipart": false,
            "fields": []
          },
          "graphql": {
            "query": "",
            "variables": ""
          }
        }
      },
      {
        "name": "IN_TRANSIT => DELIVERED order",
        "url": "http://localhost:8080/orders/f8afdb91-7496-457a-95b6-a5a07d4976a3",
        "method": "PATCH",
        "headers": [],
        "queryParams": [],
        "pathParams": [],
        "auth": {
          "type": "inherited"
        },
        "body": {
          "type": "text",
          "file": {
            "name": ""
          },
          "text": {
            "value": "{\n  \"status\": \"DELIVERED\"\n}",
            "format": "application/json"
          },
          "form": {
            "isMultipart": false,
            "fields": []
          },
          "graphql": {
            "query": "",
            "variables": ""
          }
        }
      }
    ]
  }
}